mathops/__init__.py
mathops/core.py
math_sdk-0.1.0.dist-info/License.txt.txt
math_sdk-0.1.0.dist-info/METADATA
math_sdk-0.1.0.dist-info/WHEEL
math_sdk-0.1.0.dist-info/top_level.txt
math_sdk-0.1.0.dist-info/RECORD
